[{"name":"abstract class CSContext : ContextWrapper, CSHasContext","description":"renetik.android.event.common.CSContext","location":"renetik-android-event/renetik.android.event.common/-c-s-context/index.html","searchKeys":["CSContext","abstract class CSContext : ContextWrapper, CSHasContext","renetik.android.event.common.CSContext"]},{"name":"abstract class CSPropertyBase<T>(parent: CSHasDestroy? = null, val onChange: (value: T) -> Unit? = null) : CSModel, CSProperty<T> ","description":"renetik.android.event.property.CSPropertyBase","location":"renetik-android-event/renetik.android.event.property/-c-s-property-base/index.html","searchKeys":["CSPropertyBase","abstract class CSPropertyBase<T>(parent: CSHasDestroy? = null, val onChange: (value: T) -> Unit? = null) : CSModel, CSProperty<T> ","renetik.android.event.property.CSPropertyBase"]},{"name":"abstract class CSPropertyWrapper<T>(parent: CSHasDestroy? = null) : CSModel, CSProperty<T> ","description":"renetik.android.event.property.CSPropertyWrapper","location":"renetik-android-event/renetik.android.event.property/-c-s-property-wrapper/index.html","searchKeys":["CSPropertyWrapper","abstract class CSPropertyWrapper<T>(parent: CSHasDestroy? = null) : CSModel, CSProperty<T> ","renetik.android.event.property.CSPropertyWrapper"]},{"name":"abstract fun cancel()","description":"renetik.android.event.registration.CSRegistration.cancel","location":"renetik-android-event/renetik.android.event.registration/-c-s-registration/cancel.html","searchKeys":["cancel","abstract fun cancel()","renetik.android.event.registration.CSRegistration.cancel"]},{"name":"abstract fun clear()","description":"renetik.android.event.CSEvent.clear","location":"renetik-android-event/renetik.android.event/-c-s-event/clear.html","searchKeys":["clear","abstract fun clear()","renetik.android.event.CSEvent.clear"]},{"name":"abstract fun fire(argument: T)","description":"renetik.android.event.CSEvent.fire","location":"renetik-android-event/renetik.android.event/-c-s-event/fire.html","searchKeys":["fire","abstract fun fire(argument: T)","renetik.android.event.CSEvent.fire"]},{"name":"abstract fun fireChange()","description":"renetik.android.event.property.CSProperty.fireChange","location":"renetik-android-event/renetik.android.event.property/-c-s-property/fire-change.html","searchKeys":["fireChange","abstract fun fireChange()","renetik.android.event.property.CSProperty.fireChange"]},{"name":"abstract fun invoke(argument: T)","description":"renetik.android.event.CSEventListener.invoke","location":"renetik-android-event/renetik.android.event/-c-s-event-listener/invoke.html","searchKeys":["invoke","abstract fun invoke(argument: T)","renetik.android.event.CSEventListener.invoke"]},{"name":"abstract fun listen(function: (argument: T) -> Unit): CSRegistration","description":"renetik.android.event.CSEvent.listen","location":"renetik-android-event/renetik.android.event/-c-s-event/listen.html","searchKeys":["listen","abstract fun listen(function: (argument: T) -> Unit): CSRegistration","renetik.android.event.CSEvent.listen"]},{"name":"abstract fun onChange(function: (T) -> Unit): CSRegistration","description":"renetik.android.event.property.CSProperty.onChange","location":"renetik-android-event/renetik.android.event.property/-c-s-property/on-change.html","searchKeys":["onChange","abstract fun onChange(function: (T) -> Unit): CSRegistration","renetik.android.event.property.CSProperty.onChange"]},{"name":"abstract fun onDestroy()","description":"renetik.android.event.common.CSHasDestroy.onDestroy","location":"renetik-android-event/renetik.android.event.common/-c-s-has-destroy/on-destroy.html","searchKeys":["onDestroy","abstract fun onDestroy()","renetik.android.event.common.CSHasDestroy.onDestroy"]},{"name":"abstract fun pause()","description":"renetik.android.event.CSEvent.pause","location":"renetik-android-event/renetik.android.event/-c-s-event/pause.html","searchKeys":["pause","abstract fun pause()","renetik.android.event.CSEvent.pause"]},{"name":"abstract fun pause()","description":"renetik.android.event.registration.CSRegistration.pause","location":"renetik-android-event/renetik.android.event.registration/-c-s-registration/pause.html","searchKeys":["pause","abstract fun pause()","renetik.android.event.registration.CSRegistration.pause"]},{"name":"abstract fun resume()","description":"renetik.android.event.CSEvent.resume","location":"renetik-android-event/renetik.android.event/-c-s-event/resume.html","searchKeys":["resume","abstract fun resume()","renetik.android.event.CSEvent.resume"]},{"name":"abstract fun resume()","description":"renetik.android.event.registration.CSRegistration.resume","location":"renetik-android-event/renetik.android.event.registration/-c-s-registration/resume.html","searchKeys":["resume","abstract fun resume()","renetik.android.event.registration.CSRegistration.resume"]},{"name":"abstract fun value(newValue: T, fire: Boolean = true)","description":"renetik.android.event.property.CSProperty.value","location":"renetik-android-event/renetik.android.event.property/-c-s-property/value.html","searchKeys":["value","abstract fun value(newValue: T, fire: Boolean = true)","renetik.android.event.property.CSProperty.value"]},{"name":"abstract val context: Context","description":"renetik.android.event.common.CSHasContext.context","location":"renetik-android-event/renetik.android.event.common/-c-s-has-context/context.html","searchKeys":["context","abstract val context: Context","renetik.android.event.common.CSHasContext.context"]},{"name":"abstract val eventDestroy: CSEvent<Unit>","description":"renetik.android.event.common.CSHasDestroy.eventDestroy","location":"renetik-android-event/renetik.android.event.common/-c-s-has-destroy/event-destroy.html","searchKeys":["eventDestroy","abstract val eventDestroy: CSEvent<Unit>","renetik.android.event.common.CSHasDestroy.eventDestroy"]},{"name":"abstract val isActive: Boolean","description":"renetik.android.event.registration.CSRegistration.isActive","location":"renetik-android-event/renetik.android.event.registration/-c-s-registration/is-active.html","searchKeys":["isActive","abstract val isActive: Boolean","renetik.android.event.registration.CSRegistration.isActive"]},{"name":"abstract val isCanceled: Boolean","description":"renetik.android.event.registration.CSRegistration.isCanceled","location":"renetik-android-event/renetik.android.event.registration/-c-s-registration/is-canceled.html","searchKeys":["isCanceled","abstract val isCanceled: Boolean","renetik.android.event.registration.CSRegistration.isCanceled"]},{"name":"abstract val isListened: Boolean","description":"renetik.android.event.CSEvent.isListened","location":"renetik-android-event/renetik.android.event/-c-s-event/is-listened.html","searchKeys":["isListened","abstract val isListened: Boolean","renetik.android.event.CSEvent.isListened"]},{"name":"abstract val registrations: CSRegistrations","description":"renetik.android.event.registration.CSHasRegistrations.registrations","location":"renetik-android-event/renetik.android.event.registration/-c-s-has-registrations/registrations.html","searchKeys":["registrations","abstract val registrations: CSRegistrations","renetik.android.event.registration.CSHasRegistrations.registrations"]},{"name":"class CSEventImpl<T> : CSEvent<T> ","description":"renetik.android.event.CSEventImpl","location":"renetik-android-event/renetik.android.event/-c-s-event-impl/index.html","searchKeys":["CSEventImpl","class CSEventImpl<T> : CSEvent<T> ","renetik.android.event.CSEventImpl"]},{"name":"class CSFunctionRegistration(function: ArgFunc<CSRegistration>, val onCancel: ArgFunc<Func>? = null) : CSRegistrationImpl","description":"renetik.android.event.registration.CSFunctionRegistration","location":"renetik-android-event/renetik.android.event.registration/-c-s-function-registration/index.html","searchKeys":["CSFunctionRegistration","class CSFunctionRegistration(function: ArgFunc<CSRegistration>, val onCancel: ArgFunc<Func>? = null) : CSRegistrationImpl","renetik.android.event.registration.CSFunctionRegistration"]},{"name":"class CSLateProperty<T>(onApply: (value: T) -> Unit? = null) : CSPropertyBase<T> ","description":"renetik.android.event.property.CSLateProperty","location":"renetik-android-event/renetik.android.event.property/-c-s-late-property/index.html","searchKeys":["CSLateProperty","class CSLateProperty<T>(onApply: (value: T) -> Unit? = null) : CSPropertyBase<T> ","renetik.android.event.property.CSLateProperty"]},{"name":"class CSPropertyImpl<T>(value: T, onApply: (value: T) -> Unit? = null) : CSPropertyBase<T> ","description":"renetik.android.event.property.CSPropertyImpl","location":"renetik-android-event/renetik.android.event.property/-c-s-property-impl/index.html","searchKeys":["CSPropertyImpl","class CSPropertyImpl<T>(value: T, onApply: (value: T) -> Unit? = null) : CSPropertyBase<T> ","renetik.android.event.property.CSPropertyImpl"]},{"name":"class CSRegistrations","description":"renetik.android.event.registration.CSRegistrations","location":"renetik-android-event/renetik.android.event.registration/-c-s-registrations/index.html","searchKeys":["CSRegistrations","class CSRegistrations","renetik.android.event.registration.CSRegistrations"]},{"name":"class CSSynchronizedPropertyImpl<T>(value: T, onApply: (value: T) -> Unit? = null) : CSPropertyBase<T> , CSSynchronizedProperty<T> ","description":"renetik.android.event.property.CSSynchronizedPropertyImpl","location":"renetik-android-event/renetik.android.event.property/-c-s-synchronized-property-impl/index.html","searchKeys":["CSSynchronizedPropertyImpl","class CSSynchronizedPropertyImpl<T>(value: T, onApply: (value: T) -> Unit? = null) : CSPropertyBase<T> , CSSynchronizedProperty<T> ","renetik.android.event.property.CSSynchronizedPropertyImpl"]},{"name":"class CSSynchronizedVariableImpl<T>(value: T, val onChange: (value: T) -> Unit? = null) : CSSynchronizedVariable<T> ","description":"renetik.android.event.property.CSSynchronizedVariableImpl","location":"renetik-android-event/renetik.android.event.property/-c-s-synchronized-variable-impl/index.html","searchKeys":["CSSynchronizedVariableImpl","class CSSynchronizedVariableImpl<T>(value: T, val onChange: (value: T) -> Unit? = null) : CSSynchronizedVariable<T> ","renetik.android.event.property.CSSynchronizedVariableImpl"]},{"name":"fun <T : CSHasRegistrations, CSHasDestroy> T.onDestroy(listener: () -> Unit): CSRegistration","description":"renetik.android.event.common.onDestroy","location":"renetik-android-event/renetik.android.event.common/on-destroy.html","searchKeys":["onDestroy","fun <T : CSHasRegistrations, CSHasDestroy> T.onDestroy(listener: () -> Unit): CSRegistration","renetik.android.event.common.onDestroy"]},{"name":"fun <T : CSHasRegistrations, CSHasDestroy> T.parent(parent: CSHasDestroy): T","description":"renetik.android.event.common.parent","location":"renetik-android-event/renetik.android.event.common/parent.html","searchKeys":["parent","fun <T : CSHasRegistrations, CSHasDestroy> T.parent(parent: CSHasDestroy): T","renetik.android.event.common.parent"]},{"name":"fun <T : CSProperty<*>> T.apply(): T","description":"renetik.android.event.property.apply","location":"renetik-android-event/renetik.android.event.property/apply.html","searchKeys":["apply","fun <T : CSProperty<*>> T.apply(): T","renetik.android.event.property.apply"]},{"name":"fun <T : CSProperty<Int>> T.keepMax(maxValue: Int, fire: Boolean = true): T","description":"renetik.android.event.property.keepMax","location":"renetik-android-event/renetik.android.event.property/keep-max.html","searchKeys":["keepMax","fun <T : CSProperty<Int>> T.keepMax(maxValue: Int, fire: Boolean = true): T","renetik.android.event.property.keepMax"]},{"name":"fun <T> CSLateProperty(onApply: (value: T) -> Unit? = null)","description":"renetik.android.event.property.CSLateProperty.CSLateProperty","location":"renetik-android-event/renetik.android.event.property/-c-s-late-property/-c-s-late-property.html","searchKeys":["CSLateProperty","fun <T> CSLateProperty(onApply: (value: T) -> Unit? = null)","renetik.android.event.property.CSLateProperty.CSLateProperty"]},{"name":"fun <T> CSProperty<T>.action(function: (T) -> Unit): CSRegistration","description":"renetik.android.event.property.action","location":"renetik-android-event/renetik.android.event.property/action.html","searchKeys":["action","fun <T> CSProperty<T>.action(function: (T) -> Unit): CSRegistration","renetik.android.event.property.action"]},{"name":"fun <T> CSProperty<T>.connect(property: CSProperty<T>): CSRegistration","description":"renetik.android.event.property.connect","location":"renetik-android-event/renetik.android.event.property/connect.html","searchKeys":["connect","fun <T> CSProperty<T>.connect(property: CSProperty<T>): CSRegistration","renetik.android.event.property.connect"]},{"name":"fun <T> CSProperty<T>.onChange(function: (CSRegistration, T) -> Unit): CSRegistration","description":"renetik.android.event.property.onChange","location":"renetik-android-event/renetik.android.event.property/on-change.html","searchKeys":["onChange","fun <T> CSProperty<T>.onChange(function: (CSRegistration, T) -> Unit): CSRegistration","renetik.android.event.property.onChange"]},{"name":"fun <T> CSProperty<T>.onChangeOnce(listener: (argument: T) -> Unit): CSRegistration","description":"renetik.android.event.property.onChangeOnce","location":"renetik-android-event/renetik.android.event.property/on-change-once.html","searchKeys":["onChangeOnce","fun <T> CSProperty<T>.onChangeOnce(listener: (argument: T) -> Unit): CSRegistration","renetik.android.event.property.onChangeOnce"]},{"name":"fun <T> CSProperty<T?>.clear()","description":"renetik.android.event.property.clear","location":"renetik-android-event/renetik.android.event.property/clear.html","searchKeys":["clear","fun <T> CSProperty<T?>.clear()","renetik.android.event.property.clear"]},{"name":"fun <T> CSPropertyBase(onApply: (value: T) -> Unit? = null)","description":"renetik.android.event.property.CSPropertyBase.CSPropertyBase","location":"renetik-android-event/renetik.android.event.property/-c-s-property-base/-c-s-property-base.html","searchKeys":["CSPropertyBase","fun <T> CSPropertyBase(onApply: (value: T) -> Unit? = null)","renetik.android.event.property.CSPropertyBase.CSPropertyBase"]},{"name":"fun <T> CSPropertyBase(parent: CSHasDestroy? = null, onChange: (value: T) -> Unit? = null)","description":"renetik.android.event.property.CSPropertyBase.CSPropertyBase","location":"renetik-android-event/renetik.android.event.property/-c-s-property-base/-c-s-property-base.html","searchKeys":["CSPropertyBase","fun <T> CSPropertyBase(parent: CSHasDestroy? = null, onChange: (value: T) -> Unit? = null)","renetik.android.event.property.CSPropertyBase.CSPropertyBase"]},{"name":"fun <T> CSPropertyImpl(value: T, onApply: (value: T) -> Unit? = null)","description":"renetik.android.event.property.CSPropertyImpl.CSPropertyImpl","location":"renetik-android-event/renetik.android.event.property/-c-s-property-impl/-c-s-property-impl.html","searchKeys":["CSPropertyImpl","fun <T> CSPropertyImpl(value: T, onApply: (value: T) -> Unit? = null)","renetik.android.event.property.CSPropertyImpl.CSPropertyImpl"]},{"name":"fun <T> CSSynchronizedPropertyImpl(value: T, onApply: (value: T) -> Unit? = null)","description":"renetik.android.event.property.CSSynchronizedPropertyImpl.CSSynchronizedPropertyImpl","location":"renetik-android-event/renetik.android.event.property/-c-s-synchronized-property-impl/-c-s-synchronized-property-impl.html","searchKeys":["CSSynchronizedPropertyImpl","fun <T> CSSynchronizedPropertyImpl(value: T, onApply: (value: T) -> Unit? = null)","renetik.android.event.property.CSSynchronizedPropertyImpl.CSSynchronizedPropertyImpl"]},{"name":"fun <T> CSSynchronizedVariableImpl(value: T, onChange: (value: T) -> Unit? = null)","description":"renetik.android.event.property.CSSynchronizedVariableImpl.CSSynchronizedVariableImpl","location":"renetik-android-event/renetik.android.event.property/-c-s-synchronized-variable-impl/-c-s-synchronized-variable-impl.html","searchKeys":["CSSynchronizedVariableImpl","fun <T> CSSynchronizedVariableImpl(value: T, onChange: (value: T) -> Unit? = null)","renetik.android.event.property.CSSynchronizedVariableImpl.CSSynchronizedVariableImpl"]},{"name":"fun <T> event(): CSEvent<T>","description":"renetik.android.event.CSEvent.Companion.event","location":"renetik-android-event/renetik.android.event/-c-s-event/-companion/event.html","searchKeys":["event","fun <T> event(): CSEvent<T>","renetik.android.event.CSEvent.Companion.event"]},{"name":"fun <T> lateProperty(onApply: (value: T) -> Unit? = null): CSLateProperty<T>","description":"renetik.android.event.property.CSProperty.Companion.lateProperty","location":"renetik-android-event/renetik.android.event.property/-c-s-property/-companion/late-property.html","searchKeys":["lateProperty","fun <T> lateProperty(onApply: (value: T) -> Unit? = null): CSLateProperty<T>","renetik.android.event.property.CSProperty.Companion.lateProperty"]},{"name":"fun <T> nullableProperty(onApply: (value: T?) -> Unit? = null): CSProperty<T?>","description":"renetik.android.event.property.CSProperty.Companion.nullableProperty","location":"renetik-android-event/renetik.android.event.property/-c-s-property/-companion/nullable-property.html","searchKeys":["nullableProperty","fun <T> nullableProperty(onApply: (value: T?) -> Unit? = null): CSProperty<T?>","renetik.android.event.property.CSProperty.Companion.nullableProperty"]},{"name":"fun <T> property(onApply: (value: T?) -> Unit? = null): CSProperty<T?>","description":"renetik.android.event.property.CSProperty.Companion.property","location":"renetik-android-event/renetik.android.event.property/-c-s-property/-companion/property.html","searchKeys":["property","fun <T> property(onApply: (value: T?) -> Unit? = null): CSProperty<T?>","renetik.android.event.property.CSProperty.Companion.property"]},{"name":"fun <T> property(value: T, onApply: (value: T) -> Unit? = null): CSProperty<T>","description":"renetik.android.event.property.CSProperty.Companion.property","location":"renetik-android-event/renetik.android.event.property/-c-s-property/-companion/property.html","searchKeys":["property","fun <T> property(value: T, onApply: (value: T) -> Unit? = null): CSProperty<T>","renetik.android.event.property.CSProperty.Companion.property"]},{"name":"fun <T> synchronizedProperty(property: CSProperty<T>, onApply: (value: T) -> Unit? = null): CSSynchronizedProperty<T>","description":"renetik.android.event.property.CSProperty.Companion.synchronizedProperty","location":"renetik-android-event/renetik.android.event.property/-c-s-property/-companion/synchronized-property.html","searchKeys":["synchronizedProperty","fun <T> synchronizedProperty(property: CSProperty<T>, onApply: (value: T) -> Unit? = null): CSSynchronizedProperty<T>","renetik.android.event.property.CSProperty.Companion.synchronizedProperty"]},{"name":"fun <T> synchronizedProperty(value: T, onApply: (value: T) -> Unit? = null): CSSynchronizedProperty<T>","description":"renetik.android.event.property.CSProperty.Companion.synchronizedProperty","location":"renetik-android-event/renetik.android.event.property/-c-s-property/-companion/synchronized-property.html","searchKeys":["synchronizedProperty","fun <T> synchronizedProperty(value: T, onApply: (value: T) -> Unit? = null): CSSynchronizedProperty<T>","renetik.android.event.property.CSProperty.Companion.synchronizedProperty"]},{"name":"fun CSActionInterface.start(): CSVariable<Boolean>","description":"renetik.android.event.property.start","location":"renetik-android-event/renetik.android.event.property/start.html","searchKeys":["start","fun CSActionInterface.start(): CSVariable<Boolean>","renetik.android.event.property.start"]},{"name":"fun CSActionInterface.stop(): CSVariable<Boolean>","description":"renetik.android.event.property.stop","location":"renetik-android-event/renetik.android.event.property/stop.html","searchKeys":["stop","fun CSActionInterface.stop(): CSVariable<Boolean>","renetik.android.event.property.stop"]},{"name":"fun CSContext()","description":"renetik.android.event.common.CSContext.CSContext","location":"renetik-android-event/renetik.android.event.common/-c-s-context/-c-s-context.html","searchKeys":["CSContext","fun CSContext()","renetik.android.event.common.CSContext.CSContext"]},{"name":"fun CSContext(context: Context)","description":"renetik.android.event.common.CSContext.CSContext","location":"renetik-android-event/renetik.android.event.common/-c-s-context/-c-s-context.html","searchKeys":["CSContext","fun CSContext(context: Context)","renetik.android.event.common.CSContext.CSContext"]},{"name":"fun CSContext(parent: CSContext)","description":"renetik.android.event.common.CSContext.CSContext","location":"renetik-android-event/renetik.android.event.common/-c-s-context/-c-s-context.html","searchKeys":["CSContext","fun CSContext(parent: CSContext)","renetik.android.event.common.CSContext.CSContext"]},{"name":"fun CSContext(parent: CSHasContext)","description":"renetik.android.event.common.CSContext.CSContext","location":"renetik-android-event/renetik.android.event.common/-c-s-context/-c-s-context.html","searchKeys":["CSContext","fun CSContext(parent: CSHasContext)","renetik.android.event.common.CSContext.CSContext"]},{"name":"fun CSEvent<*>.paused(function: Func)","description":"renetik.android.event.paused","location":"renetik-android-event/renetik.android.event/paused.html","searchKeys":["paused","fun CSEvent<*>.paused(function: Func)","renetik.android.event.paused"]},{"name":"fun CSEvent<Unit>.fire(): CSEvent<Unit>","description":"renetik.android.event.fire","location":"renetik-android-event/renetik.android.event/fire.html","searchKeys":["fire","fun CSEvent<Unit>.fire(): CSEvent<Unit>","renetik.android.event.fire"]},{"name":"fun CSEventImpl()","description":"renetik.android.event.CSEventImpl.CSEventImpl","location":"renetik-android-event/renetik.android.event/-c-s-event-impl/-c-s-event-impl.html","searchKeys":["CSEventImpl","fun CSEventImpl()","renetik.android.event.CSEventImpl.CSEventImpl"]},{"name":"fun CSFunctionRegistration(function: ArgFunc<CSRegistration>): CSFunctionRegistration","description":"renetik.android.event.registration.CSFunctionRegistration","location":"renetik-android-event/renetik.android.event.registration/-c-s-function-registration.html","searchKeys":["CSFunctionRegistration","fun CSFunctionRegistration(function: ArgFunc<CSRegistration>): CSFunctionRegistration","renetik.android.event.registration.CSFunctionRegistration"]},{"name":"fun CSFunctionRegistration(function: ArgFunc<CSRegistration>, onCancel: ArgFunc<Func>? = null)","description":"renetik.android.event.registration.CSFunctionRegistration.CSFunctionRegistration","location":"renetik-android-event/renetik.android.event.registration/-c-s-function-registration/-c-s-function-registration.html","searchKeys":["CSFunctionRegistration","fun CSFunctionRegistration(function: ArgFunc<CSRegistration>, onCancel: ArgFunc<Func>? = null)","renetik.android.event.registration.CSFunctionRegistration.CSFunctionRegistration"]},{"name":"fun CSHasDestroy.destroy()","description":"renetik.android.event.common.destroy","location":"renetik-android-event/renetik.android.event.common/destroy.html","searchKeys":["destroy","fun CSHasDestroy.destroy()","renetik.android.event.common.destroy"]},{"name":"fun CSHasRegistrations.cancel(registration: CSRegistration): CSRegistration","description":"renetik.android.event.registration.cancel","location":"renetik-android-event/renetik.android.event.registration/cancel.html","searchKeys":["cancel","fun CSHasRegistrations.cancel(registration: CSRegistration): CSRegistration","renetik.android.event.registration.cancel"]},{"name":"fun CSHasRegistrations.cancel(registration: CSRegistration?): Unit?","description":"renetik.android.event.registration.cancel","location":"renetik-android-event/renetik.android.event.registration/cancel.html","searchKeys":["cancel","fun CSHasRegistrations.cancel(registration: CSRegistration?): Unit?","renetik.android.event.registration.cancel"]},{"name":"fun CSHasRegistrations.cancel(registrations: List<CSRegistration>?)","description":"renetik.android.event.registration.cancel","location":"renetik-android-event/renetik.android.event.registration/cancel.html","searchKeys":["cancel","fun CSHasRegistrations.cancel(registrations: List<CSRegistration>?)","renetik.android.event.registration.cancel"]},{"name":"fun CSHasRegistrations.cancel(vararg registrations: CSRegistration?)","description":"renetik.android.event.registration.cancel","location":"renetik-android-event/renetik.android.event.registration/cancel.html","searchKeys":["cancel","fun CSHasRegistrations.cancel(vararg registrations: CSRegistration?)","renetik.android.event.registration.cancel"]},{"name":"fun CSHasRegistrations.register(key: Any, registration: CSRegistration): CSRegistration","description":"renetik.android.event.registration.register","location":"renetik-android-event/renetik.android.event.registration/register.html","searchKeys":["register","fun CSHasRegistrations.register(key: Any, registration: CSRegistration): CSRegistration","renetik.android.event.registration.register"]},{"name":"fun CSHasRegistrations.register(registration: CSRegistration): CSRegistration","description":"renetik.android.event.registration.register","location":"renetik-android-event/renetik.android.event.registration/register.html","searchKeys":["register","fun CSHasRegistrations.register(registration: CSRegistration): CSRegistration","renetik.android.event.registration.register"]},{"name":"fun CSHasRegistrations.register(registration: CSRegistration?): CSRegistration?","description":"renetik.android.event.registration.register","location":"renetik-android-event/renetik.android.event.registration/register.html","searchKeys":["register","fun CSHasRegistrations.register(registration: CSRegistration?): CSRegistration?","renetik.android.event.registration.register"]},{"name":"fun CSModel(parent: CSHasDestroy? = null)","description":"renetik.android.event.common.CSModel.CSModel","location":"renetik-android-event/renetik.android.event.common/-c-s-model/-c-s-model.html","searchKeys":["CSModel","fun CSModel(parent: CSHasDestroy? = null)","renetik.android.event.common.CSModel.CSModel"]},{"name":"fun CSMultiRegistration(vararg registrations: CSRegistration): CSRegistrationImpl","description":"renetik.android.event.registration.CSMultiRegistration","location":"renetik-android-event/renetik.android.event.registration/-c-s-multi-registration.html","searchKeys":["CSMultiRegistration","fun CSMultiRegistration(vararg registrations: CSRegistration): CSRegistrationImpl","renetik.android.event.registration.CSMultiRegistration"]},{"name":"fun CSProperty<Boolean>.actionFalse(function: () -> Unit): CSRegistration","description":"renetik.android.event.property.actionFalse","location":"renetik-android-event/renetik.android.event.property/action-false.html","searchKeys":["actionFalse","fun CSProperty<Boolean>.actionFalse(function: () -> Unit): CSRegistration","renetik.android.event.property.actionFalse"]},{"name":"fun CSProperty<Boolean>.actionTrue(function: () -> Unit): CSRegistration","description":"renetik.android.event.property.actionTrue","location":"renetik-android-event/renetik.android.event.property/action-true.html","searchKeys":["actionTrue","fun CSProperty<Boolean>.actionTrue(function: () -> Unit): CSRegistration","renetik.android.event.property.actionTrue"]},{"name":"fun CSProperty<Boolean>.listenUntilFalseOnce(listener: (argument: Boolean) -> Unit): CSRegistration","description":"renetik.android.event.property.listenUntilFalseOnce","location":"renetik-android-event/renetik.android.event.property/listen-until-false-once.html","searchKeys":["listenUntilFalseOnce","fun CSProperty<Boolean>.listenUntilFalseOnce(listener: (argument: Boolean) -> Unit): CSRegistration","renetik.android.event.property.listenUntilFalseOnce"]},{"name":"fun CSProperty<Boolean>.listenUntilTrueOnce(listener: (argument: Boolean) -> Unit): CSRegistration","description":"renetik.android.event.property.listenUntilTrueOnce","location":"renetik-android-event/renetik.android.event.property/listen-until-true-once.html","searchKeys":["listenUntilTrueOnce","fun CSProperty<Boolean>.listenUntilTrueOnce(listener: (argument: Boolean) -> Unit): CSRegistration","renetik.android.event.property.listenUntilTrueOnce"]},{"name":"fun CSProperty<Boolean>.onFalse(function: () -> Unit): CSRegistration","description":"renetik.android.event.property.onFalse","location":"renetik-android-event/renetik.android.event.property/on-false.html","searchKeys":["onFalse","fun CSProperty<Boolean>.onFalse(function: () -> Unit): CSRegistration","renetik.android.event.property.onFalse"]},{"name":"fun CSProperty<Boolean>.onTrue(function: () -> Unit): CSRegistration","description":"renetik.android.event.property.onTrue","location":"renetik-android-event/renetik.android.event.property/on-true.html","searchKeys":["onTrue","fun CSProperty<Boolean>.onTrue(function: () -> Unit): CSRegistration","renetik.android.event.property.onTrue"]},{"name":"fun CSPropertyWrapper(parent: CSHasDestroy? = null)","description":"renetik.android.event.property.CSPropertyWrapper.CSPropertyWrapper","location":"renetik-android-event/renetik.android.event.property/-c-s-property-wrapper/-c-s-property-wrapper.html","searchKeys":["CSPropertyWrapper","fun CSPropertyWrapper(parent: CSHasDestroy? = null)","renetik.android.event.property.CSPropertyWrapper.CSPropertyWrapper"]},{"name":"fun CSRegistration(onResume: ArgFunc<CSRegistration>? = null, onPause: ArgFunc<CSRegistration>? = null, onCancel: ArgFunc<CSRegistration>? = null): CSRegistrationImpl","description":"renetik.android.event.registration.CSRegistration.Companion.CSRegistration","location":"renetik-android-event/renetik.android.event.registration/-c-s-registration/-companion/-c-s-registration.html","searchKeys":["CSRegistration","fun CSRegistration(onResume: ArgFunc<CSRegistration>? = null, onPause: ArgFunc<CSRegistration>? = null, onCancel: ArgFunc<CSRegistration>? = null): CSRegistrationImpl","renetik.android.event.registration.CSRegistration.Companion.CSRegistration"]},{"name":"fun CSRegistration.paused(): Closeable","description":"renetik.android.event.registration.paused","location":"renetik-android-event/renetik.android.event.registration/paused.html","searchKeys":["paused","fun CSRegistration.paused(): Closeable","renetik.android.event.registration.paused"]},{"name":"fun CSRegistration.paused(function: Func)","description":"renetik.android.event.registration.paused","location":"renetik-android-event/renetik.android.event.registration/paused.html","searchKeys":["paused","fun CSRegistration.paused(function: Func)","renetik.android.event.registration.paused"]},{"name":"fun CSRegistration.setActive(active: Boolean)","description":"renetik.android.event.registration.setActive","location":"renetik-android-event/renetik.android.event.registration/set-active.html","searchKeys":["setActive","fun CSRegistration.setActive(active: Boolean)","renetik.android.event.registration.setActive"]},{"name":"fun CSRegistrationImpl()","description":"renetik.android.event.registration.CSRegistrationImpl.CSRegistrationImpl","location":"renetik-android-event/renetik.android.event.registration/-c-s-registration-impl/-c-s-registration-impl.html","searchKeys":["CSRegistrationImpl","fun CSRegistrationImpl()","renetik.android.event.registration.CSRegistrationImpl.CSRegistrationImpl"]},{"name":"fun CSRegistrations()","description":"renetik.android.event.registration.CSRegistrations.CSRegistrations","location":"renetik-android-event/renetik.android.event.registration/-c-s-registrations/-c-s-registrations.html","searchKeys":["CSRegistrations","fun CSRegistrations()","renetik.android.event.registration.CSRegistrations.CSRegistrations"]},{"name":"fun CSVariable<Boolean>.connect(property: CSProperty<Boolean>): CSRegistration","description":"renetik.android.event.property.connect","location":"renetik-android-event/renetik.android.event.property/connect.html","searchKeys":["connect","fun CSVariable<Boolean>.connect(property: CSProperty<Boolean>): CSRegistration","renetik.android.event.property.connect"]},{"name":"fun EventListenerImpl(listener: (T) -> Unit)","description":"renetik.android.event.CSEventImpl.EventListenerImpl.EventListenerImpl","location":"renetik-android-event/renetik.android.event/-c-s-event-impl/-event-listener-impl/-event-listener-impl.html","searchKeys":["EventListenerImpl","fun EventListenerImpl(listener: (T) -> Unit)","renetik.android.event.CSEventImpl.EventListenerImpl.EventListenerImpl"]},{"name":"fun List<CSRegistration>.paused(function: Func)","description":"renetik.android.event.registration.paused","location":"renetik-android-event/renetik.android.event.registration/paused.html","searchKeys":["paused","fun List<CSRegistration>.paused(function: Func)","renetik.android.event.registration.paused"]},{"name":"fun action(): CSActionInterface","description":"renetik.android.event.property.CSAction.action","location":"renetik-android-event/renetik.android.event.property/-c-s-action/action.html","searchKeys":["action","fun action(): CSActionInterface","renetik.android.event.property.CSAction.action"]},{"name":"fun add(key: Any, registration: CSRegistration): CSRegistration","description":"renetik.android.event.registration.CSRegistrations.add","location":"renetik-android-event/renetik.android.event.registration/-c-s-registrations/add.html","searchKeys":["add","fun add(key: Any, registration: CSRegistration): CSRegistration","renetik.android.event.registration.CSRegistrations.add"]},{"name":"fun add(registration: CSRegistration): CSRegistration","description":"renetik.android.event.registration.CSRegistrations.add","location":"renetik-android-event/renetik.android.event.registration/-c-s-registrations/add.html","searchKeys":["add","fun add(registration: CSRegistration): CSRegistration","renetik.android.event.registration.CSRegistrations.add"]},{"name":"fun cancel()","description":"renetik.android.event.registration.CSRegistrations.cancel","location":"renetik-android-event/renetik.android.event.registration/-c-s-registrations/cancel.html","searchKeys":["cancel","fun cancel()","renetik.android.event.registration.CSRegistrations.cancel"]},{"name":"fun cancel(registration: CSRegistration)","description":"renetik.android.event.registration.CSRegistrations.cancel","location":"renetik-android-event/renetik.android.event.registration/-c-s-registrations/cancel.html","searchKeys":["cancel","fun cancel(registration: CSRegistration)","renetik.android.event.registration.CSRegistrations.cancel"]},{"name":"fun invoke()","description":"renetik.android.event.registration.CSFunctionRegistration.invoke","location":"renetik-android-event/renetik.android.event.registration/-c-s-function-registration/invoke.html","searchKeys":["invoke","fun invoke()","renetik.android.event.registration.CSFunctionRegistration.invoke"]},{"name":"fun later(delayMilliseconds: Int, function: () -> Unit): CSRegistration","description":"renetik.android.event.util.CSLater.later","location":"renetik-android-event/renetik.android.event.util/-c-s-later/later.html","searchKeys":["later","fun later(delayMilliseconds: Int, function: () -> Unit): CSRegistration","renetik.android.event.util.CSLater.later"]},{"name":"fun later(function: () -> Unit): CSRegistration","description":"renetik.android.event.util.CSLater.later","location":"renetik-android-event/renetik.android.event.util/-c-s-later/later.html","searchKeys":["later","fun later(function: () -> Unit): CSRegistration","renetik.android.event.util.CSLater.later"]},{"name":"fun pause(vararg registrations: CSRegistration, function: Func)","description":"renetik.android.event.registration.CSRegistration.Companion.pause","location":"renetik-android-event/renetik.android.event.registration/-c-s-registration/-companion/pause.html","searchKeys":["pause","fun pause(vararg registrations: CSRegistration, function: Func)","renetik.android.event.registration.CSRegistration.Companion.pause"]},{"name":"fun remove(listener: CSEventListener<T>)","description":"renetik.android.event.CSEventImpl.remove","location":"renetik-android-event/renetik.android.event/-c-s-event-impl/remove.html","searchKeys":["remove","fun remove(listener: CSEventListener<T>)","renetik.android.event.CSEventImpl.remove"]},{"name":"fun setActive(active: Boolean)","description":"renetik.android.event.registration.CSRegistrations.setActive","location":"renetik-android-event/renetik.android.event.registration/-c-s-registrations/set-active.html","searchKeys":["setActive","fun setActive(active: Boolean)","renetik.android.event.registration.CSRegistrations.setActive"]},{"name":"fun value(value: T)","description":"renetik.android.event.property.CSSynchronizedVariableImpl.value","location":"renetik-android-event/renetik.android.event.property/-c-s-synchronized-variable-impl/value.html","searchKeys":["value","fun value(value: T)","renetik.android.event.property.CSSynchronizedVariableImpl.value"]},{"name":"inline fun <T> CSEvent<T>.listen(crossinline function: (registration: CSRegistration, argument: T) -> Unit): CSRegistration","description":"renetik.android.event.listen","location":"renetik-android-event/renetik.android.event/listen.html","searchKeys":["listen","inline fun <T> CSEvent<T>.listen(crossinline function: (registration: CSRegistration, argument: T) -> Unit): CSRegistration","renetik.android.event.listen"]},{"name":"inline fun <T> CSEvent<T>.listenOnce(crossinline listener: (argument: T) -> Unit): CSRegistration","description":"renetik.android.event.listenOnce","location":"renetik-android-event/renetik.android.event/listen-once.html","searchKeys":["listenOnce","inline fun <T> CSEvent<T>.listenOnce(crossinline listener: (argument: T) -> Unit): CSRegistration","renetik.android.event.listenOnce"]},{"name":"inline fun <T> CSHasRegistrations.listenOnce(event: CSEvent<T>, crossinline listener: (argument: T) -> Unit): CSRegistration","description":"renetik.android.event.registration.listenOnce","location":"renetik-android-event/renetik.android.event.registration/listen-once.html","searchKeys":["listenOnce","inline fun <T> CSHasRegistrations.listenOnce(event: CSEvent<T>, crossinline listener: (argument: T) -> Unit): CSRegistration","renetik.android.event.registration.listenOnce"]},{"name":"inline fun CSEvent<*>.action(crossinline function: () -> Unit): CSRegistration","description":"renetik.android.event.action","location":"renetik-android-event/renetik.android.event/action.html","searchKeys":["action","inline fun CSEvent<*>.action(crossinline function: () -> Unit): CSRegistration","renetik.android.event.action"]},{"name":"inline fun CSEvent<Unit>.listen(crossinline function: () -> Unit): CSRegistration","description":"renetik.android.event.listen","location":"renetik-android-event/renetik.android.event/listen.html","searchKeys":["listen","inline fun CSEvent<Unit>.listen(crossinline function: () -> Unit): CSRegistration","renetik.android.event.listen"]},{"name":"inner class EventListenerImpl(listener: (T) -> Unit) : CSRegistrationImpl, CSEventListener<T> ","description":"renetik.android.event.CSEventImpl.EventListenerImpl","location":"renetik-android-event/renetik.android.event/-c-s-event-impl/-event-listener-impl/index.html","searchKeys":["EventListenerImpl","inner class EventListenerImpl(listener: (T) -> Unit) : CSRegistrationImpl, CSEventListener<T> ","renetik.android.event.CSEventImpl.EventListenerImpl"]},{"name":"interface CSEvent<T>","description":"renetik.android.event.CSEvent","location":"renetik-android-event/renetik.android.event/-c-s-event/index.html","searchKeys":["CSEvent","interface CSEvent<T>","renetik.android.event.CSEvent"]},{"name":"interface CSEventListener<T> : CSRegistration","description":"renetik.android.event.CSEventListener","location":"renetik-android-event/renetik.android.event/-c-s-event-listener/index.html","searchKeys":["CSEventListener","interface CSEventListener<T> : CSRegistration","renetik.android.event.CSEventListener"]},{"name":"interface CSHasContext : CSHasRegistrationsHasDestroy","description":"renetik.android.event.common.CSHasContext","location":"renetik-android-event/renetik.android.event.common/-c-s-has-context/index.html","searchKeys":["CSHasContext","interface CSHasContext : CSHasRegistrationsHasDestroy","renetik.android.event.common.CSHasContext"]},{"name":"interface CSHasDestroy","description":"renetik.android.event.common.CSHasDestroy","location":"renetik-android-event/renetik.android.event.common/-c-s-has-destroy/index.html","searchKeys":["CSHasDestroy","interface CSHasDestroy","renetik.android.event.common.CSHasDestroy"]},{"name":"interface CSHasRegistrations","description":"renetik.android.event.registration.CSHasRegistrations","location":"renetik-android-event/renetik.android.event.registration/-c-s-has-registrations/index.html","searchKeys":["CSHasRegistrations","interface CSHasRegistrations","renetik.android.event.registration.CSHasRegistrations"]},{"name":"interface CSHasRegistrationsHasDestroy : CSHasRegistrations, CSHasDestroy","description":"renetik.android.event.common.CSHasRegistrationsHasDestroy","location":"renetik-android-event/renetik.android.event.common/-c-s-has-registrations-has-destroy/index.html","searchKeys":["CSHasRegistrationsHasDestroy","interface CSHasRegistrationsHasDestroy : CSHasRegistrations, CSHasDestroy","renetik.android.event.common.CSHasRegistrationsHasDestroy"]},{"name":"interface CSListValuesProperty<T> : CSListValuesVariable<T> , CSProperty<T> ","description":"renetik.android.event.property.CSListValuesProperty","location":"renetik-android-event/renetik.android.event.property/-c-s-list-values-property/index.html","searchKeys":["CSListValuesProperty","interface CSListValuesProperty<T> : CSListValuesVariable<T> , CSProperty<T> ","renetik.android.event.property.CSListValuesProperty"]},{"name":"interface CSProperty<T> : CSVariable<T> ","description":"renetik.android.event.property.CSProperty","location":"renetik-android-event/renetik.android.event.property/-c-s-property/index.html","searchKeys":["CSProperty","interface CSProperty<T> : CSVariable<T> ","renetik.android.event.property.CSProperty"]},{"name":"interface CSRegistration","description":"renetik.android.event.registration.CSRegistration","location":"renetik-android-event/renetik.android.event.registration/-c-s-registration/index.html","searchKeys":["CSRegistration","interface CSRegistration","renetik.android.event.registration.CSRegistration"]},{"name":"interface CSSynchronizedProperty<T> : CSSynchronizedVariable<T> , CSProperty<T> ","description":"renetik.android.event.property.CSSynchronizedProperty","location":"renetik-android-event/renetik.android.event.property/-c-s-synchronized-property/index.html","searchKeys":["CSSynchronizedProperty","interface CSSynchronizedProperty<T> : CSSynchronizedVariable<T> , CSProperty<T> ","renetik.android.event.property.CSSynchronizedProperty"]},{"name":"interface CSSynchronizedVariable<T> : CSSynchronizedValue<T> , CSVariable<T> ","description":"renetik.android.event.property.CSSynchronizedVariable","location":"renetik-android-event/renetik.android.event.property/-c-s-synchronized-variable/index.html","searchKeys":["CSSynchronizedVariable","interface CSSynchronizedVariable<T> : CSSynchronizedValue<T> , CSVariable<T> ","renetik.android.event.property.CSSynchronizedVariable"]},{"name":"object CSAction","description":"renetik.android.event.property.CSAction","location":"renetik-android-event/renetik.android.event.property/-c-s-action/index.html","searchKeys":["CSAction","object CSAction","renetik.android.event.property.CSAction"]},{"name":"object CSLater","description":"renetik.android.event.util.CSLater","location":"renetik-android-event/renetik.android.event.util/-c-s-later/index.html","searchKeys":["CSLater","object CSLater","renetik.android.event.util.CSLater"]},{"name":"object Companion","description":"renetik.android.event.CSEvent.Companion","location":"renetik-android-event/renetik.android.event/-c-s-event/-companion/index.html","searchKeys":["Companion","object Companion","renetik.android.event.CSEvent.Companion"]},{"name":"object Companion","description":"renetik.android.event.property.CSProperty.Companion","location":"renetik-android-event/renetik.android.event.property/-c-s-property/-companion/index.html","searchKeys":["Companion","object Companion","renetik.android.event.property.CSProperty.Companion"]},{"name":"object Companion","description":"renetik.android.event.registration.CSHasRegistrations.Companion","location":"renetik-android-event/renetik.android.event.registration/-c-s-has-registrations/-companion/index.html","searchKeys":["Companion","object Companion","renetik.android.event.registration.CSHasRegistrations.Companion"]},{"name":"object Companion","description":"renetik.android.event.registration.CSRegistration.Companion","location":"renetik-android-event/renetik.android.event.registration/-c-s-registration/-companion/index.html","searchKeys":["Companion","object Companion","renetik.android.event.registration.CSRegistration.Companion"]},{"name":"open class CSModel(parent: CSHasDestroy? = null) : CSHasRegistrationsHasDestroy","description":"renetik.android.event.common.CSModel","location":"renetik-android-event/renetik.android.event.common/-c-s-model/index.html","searchKeys":["CSModel","open class CSModel(parent: CSHasDestroy? = null) : CSHasRegistrationsHasDestroy","renetik.android.event.common.CSModel"]},{"name":"open class CSRegistrationImpl : CSRegistration","description":"renetik.android.event.registration.CSRegistrationImpl","location":"renetik-android-event/renetik.android.event.registration/-c-s-registration-impl/index.html","searchKeys":["CSRegistrationImpl","open class CSRegistrationImpl : CSRegistration","renetik.android.event.registration.CSRegistrationImpl"]},{"name":"open fun <T : Any> T.onMain(function: T.() -> Unit): CSRegistration?","description":"renetik.android.event.registration.CSHasRegistrations.onMain","location":"renetik-android-event/renetik.android.event.registration/-c-s-has-registrations/on-main.html","searchKeys":["onMain","open fun <T : Any> T.onMain(function: T.() -> Unit): CSRegistration?","renetik.android.event.registration.CSHasRegistrations.onMain"]},{"name":"open fun later(delayMilliseconds: Int, function: () -> Unit): CSRegistration","description":"renetik.android.event.registration.CSHasRegistrations.later","location":"renetik-android-event/renetik.android.event.registration/-c-s-has-registrations/later.html","searchKeys":["later","open fun later(delayMilliseconds: Int, function: () -> Unit): CSRegistration","renetik.android.event.registration.CSHasRegistrations.later"]},{"name":"open fun later(function: () -> Unit): CSRegistration","description":"renetik.android.event.registration.CSHasRegistrations.later","location":"renetik-android-event/renetik.android.event.registration/-c-s-has-registrations/later.html","searchKeys":["later","open fun later(function: () -> Unit): CSRegistration","renetik.android.event.registration.CSHasRegistrations.later"]},{"name":"open fun onValueChanged(newValue: T, fire: Boolean = true)","description":"renetik.android.event.property.CSPropertyBase.onValueChanged","location":"renetik-android-event/renetik.android.event.property/-c-s-property-base/on-value-changed.html","searchKeys":["onValueChanged","open fun onValueChanged(newValue: T, fire: Boolean = true)","renetik.android.event.property.CSPropertyBase.onValueChanged"]},{"name":"open override fun cancel()","description":"renetik.android.event.CSEventImpl.EventListenerImpl.cancel","location":"renetik-android-event/renetik.android.event/-c-s-event-impl/-event-listener-impl/cancel.html","searchKeys":["cancel","open override fun cancel()","renetik.android.event.CSEventImpl.EventListenerImpl.cancel"]},{"name":"open override fun cancel()","description":"renetik.android.event.registration.CSFunctionRegistration.cancel","location":"renetik-android-event/renetik.android.event.registration/-c-s-function-registration/cancel.html","searchKeys":["cancel","open override fun cancel()","renetik.android.event.registration.CSFunctionRegistration.cancel"]},{"name":"open override fun cancel()","description":"renetik.android.event.registration.CSRegistrationImpl.cancel","location":"renetik-android-event/renetik.android.event.registration/-c-s-registration-impl/cancel.html","searchKeys":["cancel","open override fun cancel()","renetik.android.event.registration.CSRegistrationImpl.cancel"]},{"name":"open override fun clear()","description":"renetik.android.event.CSEventImpl.clear","location":"renetik-android-event/renetik.android.event/-c-s-event-impl/clear.html","searchKeys":["clear","open override fun clear()","renetik.android.event.CSEventImpl.clear"]},{"name":"open override fun fire(argument: T)","description":"renetik.android.event.CSEventImpl.fire","location":"renetik-android-event/renetik.android.event/-c-s-event-impl/fire.html","searchKeys":["fire","open override fun fire(argument: T)","renetik.android.event.CSEventImpl.fire"]},{"name":"open override fun fireChange()","description":"renetik.android.event.property.CSPropertyBase.fireChange","location":"renetik-android-event/renetik.android.event.property/-c-s-property-base/fire-change.html","searchKeys":["fireChange","open override fun fireChange()","renetik.android.event.property.CSPropertyBase.fireChange"]},{"name":"open override fun fireChange()","description":"renetik.android.event.property.CSPropertyWrapper.fireChange","location":"renetik-android-event/renetik.android.event.property/-c-s-property-wrapper/fire-change.html","searchKeys":["fireChange","open override fun fireChange()","renetik.android.event.property.CSPropertyWrapper.fireChange"]},{"name":"open override fun invoke(argument: T)","description":"renetik.android.event.CSEventImpl.EventListenerImpl.invoke","location":"renetik-android-event/renetik.android.event/-c-s-event-impl/-event-listener-impl/invoke.html","searchKeys":["invoke","open override fun invoke(argument: T)","renetik.android.event.CSEventImpl.EventListenerImpl.invoke"]},{"name":"open override fun listen(function: (T) -> Unit): CSRegistration","description":"renetik.android.event.CSEventImpl.listen","location":"renetik-android-event/renetik.android.event/-c-s-event-impl/listen.html","searchKeys":["listen","open override fun listen(function: (T) -> Unit): CSRegistration","renetik.android.event.CSEventImpl.listen"]},{"name":"open override fun onChange(function: (T) -> Unit): CSRegistration","description":"renetik.android.event.property.CSPropertyBase.onChange","location":"renetik-android-event/renetik.android.event.property/-c-s-property-base/on-change.html","searchKeys":["onChange","open override fun onChange(function: (T) -> Unit): CSRegistration","renetik.android.event.property.CSPropertyBase.onChange"]},{"name":"open override fun onChange(function: (T) -> Unit): CSRegistration","description":"renetik.android.event.property.CSPropertyWrapper.onChange","location":"renetik-android-event/renetik.android.event.property/-c-s-property-wrapper/on-change.html","searchKeys":["onChange","open override fun onChange(function: (T) -> Unit): CSRegistration","renetik.android.event.property.CSPropertyWrapper.onChange"]},{"name":"open override fun onDestroy()","description":"renetik.android.event.common.CSContext.onDestroy","location":"renetik-android-event/renetik.android.event.common/-c-s-context/on-destroy.html","searchKeys":["onDestroy","open override fun onDestroy()","renetik.android.event.common.CSContext.onDestroy"]},{"name":"open override fun onDestroy()","description":"renetik.android.event.common.CSModel.onDestroy","location":"renetik-android-event/renetik.android.event.common/-c-s-model/on-destroy.html","searchKeys":["onDestroy","open override fun onDestroy()","renetik.android.event.common.CSModel.onDestroy"]},{"name":"open override fun pause()","description":"renetik.android.event.CSEventImpl.pause","location":"renetik-android-event/renetik.android.event/-c-s-event-impl/pause.html","searchKeys":["pause","open override fun pause()","renetik.android.event.CSEventImpl.pause"]},{"name":"open override fun pause()","description":"renetik.android.event.registration.CSRegistrationImpl.pause","location":"renetik-android-event/renetik.android.event.registration/-c-s-registration-impl/pause.html","searchKeys":["pause","open override fun pause()","renetik.android.event.registration.CSRegistrationImpl.pause"]},{"name":"open override fun resume()","description":"renetik.android.event.CSEventImpl.resume","location":"renetik-android-event/renetik.android.event/-c-s-event-impl/resume.html","searchKeys":["resume","open override fun resume()","renetik.android.event.CSEventImpl.resume"]},{"name":"open override fun resume()","description":"renetik.android.event.registration.CSRegistrationImpl.resume","location":"renetik-android-event/renetik.android.event.registration/-c-s-registration-impl/resume.html","searchKeys":["resume","open override fun resume()","renetik.android.event.registration.CSRegistrationImpl.resume"]},{"name":"open override fun toString(): String","description":"renetik.android.event.property.CSPropertyBase.toString","location":"renetik-android-event/renetik.android.event.property/-c-s-property-base/to-string.html","searchKeys":["toString","open override fun toString(): String","renetik.android.event.property.CSPropertyBase.toString"]},{"name":"open override fun unregisterReceiver(receiver: BroadcastReceiver)","description":"renetik.android.event.common.CSContext.unregisterReceiver","location":"renetik-android-event/renetik.android.event.common/-c-s-context/unregister-receiver.html","searchKeys":["unregisterReceiver","open override fun unregisterReceiver(receiver: BroadcastReceiver)","renetik.android.event.common.CSContext.unregisterReceiver"]},{"name":"open override fun value(newValue: T, fire: Boolean)","description":"renetik.android.event.property.CSLateProperty.value","location":"renetik-android-event/renetik.android.event.property/-c-s-late-property/value.html","searchKeys":["value","open override fun value(newValue: T, fire: Boolean)","renetik.android.event.property.CSLateProperty.value"]},{"name":"open override fun value(newValue: T, fire: Boolean)","description":"renetik.android.event.property.CSPropertyImpl.value","location":"renetik-android-event/renetik.android.event.property/-c-s-property-impl/value.html","searchKeys":["value","open override fun value(newValue: T, fire: Boolean)","renetik.android.event.property.CSPropertyImpl.value"]},{"name":"open override fun value(newValue: T, fire: Boolean)","description":"renetik.android.event.property.CSPropertyWrapper.value","location":"renetik-android-event/renetik.android.event.property/-c-s-property-wrapper/value.html","searchKeys":["value","open override fun value(newValue: T, fire: Boolean)","renetik.android.event.property.CSPropertyWrapper.value"]},{"name":"open override fun value(newValue: T, fire: Boolean)","description":"renetik.android.event.property.CSSynchronizedPropertyImpl.value","location":"renetik-android-event/renetik.android.event.property/-c-s-synchronized-property-impl/value.html","searchKeys":["value","open override fun value(newValue: T, fire: Boolean)","renetik.android.event.property.CSSynchronizedPropertyImpl.value"]},{"name":"open override val context: Context","description":"renetik.android.event.common.CSContext.context","location":"renetik-android-event/renetik.android.event.common/-c-s-context/context.html","searchKeys":["context","open override val context: Context","renetik.android.event.common.CSContext.context"]},{"name":"open override val eventDestroy: CSEvent<Unit>","description":"renetik.android.event.common.CSContext.eventDestroy","location":"renetik-android-event/renetik.android.event.common/-c-s-context/event-destroy.html","searchKeys":["eventDestroy","open override val eventDestroy: CSEvent<Unit>","renetik.android.event.common.CSContext.eventDestroy"]},{"name":"open override val eventDestroy: CSEvent<Unit>","description":"renetik.android.event.common.CSModel.eventDestroy","location":"renetik-android-event/renetik.android.event.common/-c-s-model/event-destroy.html","searchKeys":["eventDestroy","open override val eventDestroy: CSEvent<Unit>","renetik.android.event.common.CSModel.eventDestroy"]},{"name":"open override val isListened: Boolean","description":"renetik.android.event.CSEventImpl.isListened","location":"renetik-android-event/renetik.android.event/-c-s-event-impl/is-listened.html","searchKeys":["isListened","open override val isListened: Boolean","renetik.android.event.CSEventImpl.isListened"]},{"name":"open override var isActive: Boolean = true","description":"renetik.android.event.registration.CSRegistrationImpl.isActive","location":"renetik-android-event/renetik.android.event.registration/-c-s-registration-impl/is-active.html","searchKeys":["isActive","open override var isActive: Boolean = true","renetik.android.event.registration.CSRegistrationImpl.isActive"]},{"name":"open override var isCanceled: Boolean = false","description":"renetik.android.event.registration.CSRegistrationImpl.isCanceled","location":"renetik-android-event/renetik.android.event.registration/-c-s-registration-impl/is-canceled.html","searchKeys":["isCanceled","open override var isCanceled: Boolean = false","renetik.android.event.registration.CSRegistrationImpl.isCanceled"]},{"name":"open override var value: T","description":"renetik.android.event.property.CSLateProperty.value","location":"renetik-android-event/renetik.android.event.property/-c-s-late-property/value.html","searchKeys":["value","open override var value: T","renetik.android.event.property.CSLateProperty.value"]},{"name":"open override var value: T","description":"renetik.android.event.property.CSPropertyImpl.value","location":"renetik-android-event/renetik.android.event.property/-c-s-property-impl/value.html","searchKeys":["value","open override var value: T","renetik.android.event.property.CSPropertyImpl.value"]},{"name":"open override var value: T","description":"renetik.android.event.property.CSPropertyWrapper.value","location":"renetik-android-event/renetik.android.event.property/-c-s-property-wrapper/value.html","searchKeys":["value","open override var value: T","renetik.android.event.property.CSPropertyWrapper.value"]},{"name":"open override var value: T","description":"renetik.android.event.property.CSSynchronizedPropertyImpl.value","location":"renetik-android-event/renetik.android.event.property/-c-s-synchronized-property-impl/value.html","searchKeys":["value","open override var value: T","renetik.android.event.property.CSSynchronizedPropertyImpl.value"]},{"name":"open override var value: T","description":"renetik.android.event.property.CSSynchronizedVariableImpl.value","location":"renetik-android-event/renetik.android.event.property/-c-s-synchronized-variable-impl/value.html","searchKeys":["value","open override var value: T","renetik.android.event.property.CSSynchronizedVariableImpl.value"]},{"name":"override val registrations: CSRegistrations","description":"renetik.android.event.common.CSContext.registrations","location":"renetik-android-event/renetik.android.event.common/-c-s-context/registrations.html","searchKeys":["registrations","override val registrations: CSRegistrations","renetik.android.event.common.CSContext.registrations"]},{"name":"override val registrations: CSRegistrations","description":"renetik.android.event.common.CSModel.registrations","location":"renetik-android-event/renetik.android.event.common/-c-s-model/registrations.html","searchKeys":["registrations","override val registrations: CSRegistrations","renetik.android.event.common.CSModel.registrations"]},{"name":"val <T> CSProperty<T?>.isEmpty: Boolean","description":"renetik.android.event.property.isEmpty","location":"renetik-android-event/renetik.android.event.property/is-empty.html","searchKeys":["isEmpty","val <T> CSProperty<T?>.isEmpty: Boolean","renetik.android.event.property.isEmpty"]},{"name":"val <T> CSProperty<T?>.isSet: Boolean","description":"renetik.android.event.property.isSet","location":"renetik-android-event/renetik.android.event.property/is-set.html","searchKeys":["isSet","val <T> CSProperty<T?>.isSet: Boolean","renetik.android.event.property.isSet"]},{"name":"val CSActionInterface.isRunning: Boolean","description":"renetik.android.event.property.isRunning","location":"renetik-android-event/renetik.android.event.property/is-running.html","searchKeys":["isRunning","val CSActionInterface.isRunning: Boolean","renetik.android.event.property.isRunning"]},{"name":"val associated: CSAssociation","description":"renetik.android.event.common.CSModel.associated","location":"renetik-android-event/renetik.android.event.common/-c-s-model/associated.html","searchKeys":["associated","val associated: CSAssociation","renetik.android.event.common.CSModel.associated"]},{"name":"val eventChange: CSEvent<T>","description":"renetik.android.event.property.CSPropertyBase.eventChange","location":"renetik-android-event/renetik.android.event.property/-c-s-property-base/event-change.html","searchKeys":["eventChange","val eventChange: CSEvent<T>","renetik.android.event.property.CSPropertyBase.eventChange"]},{"name":"val function: Func","description":"renetik.android.event.registration.CSFunctionRegistration.function","location":"renetik-android-event/renetik.android.event.registration/-c-s-function-registration/function.html","searchKeys":["function","val function: Func","renetik.android.event.registration.CSFunctionRegistration.function"]},{"name":"val onCancel: ArgFunc<Func>? = null","description":"renetik.android.event.registration.CSFunctionRegistration.onCancel","location":"renetik-android-event/renetik.android.event.registration/-c-s-function-registration/on-cancel.html","searchKeys":["onCancel","val onCancel: ArgFunc<Func>? = null","renetik.android.event.registration.CSFunctionRegistration.onCancel"]},{"name":"val onChange: (value: T) -> Unit? = null","description":"renetik.android.event.property.CSPropertyBase.onChange","location":"renetik-android-event/renetik.android.event.property/-c-s-property-base/on-change.html","searchKeys":["onChange","val onChange: (value: T) -> Unit? = null","renetik.android.event.property.CSPropertyBase.onChange"]},{"name":"val onChange: (value: T) -> Unit? = null","description":"renetik.android.event.property.CSSynchronizedVariableImpl.onChange","location":"renetik-android-event/renetik.android.event.property/-c-s-synchronized-variable-impl/on-change.html","searchKeys":["onChange","val onChange: (value: T) -> Unit? = null","renetik.android.event.property.CSSynchronizedVariableImpl.onChange"]},{"name":"val registrations: MutableMap<Any, CSRegistration>","description":"renetik.android.event.registration.CSRegistrations.registrations","location":"renetik-android-event/renetik.android.event.registration/-c-s-registrations/registrations.html","searchKeys":["registrations","val registrations: MutableMap<Any, CSRegistration>","renetik.android.event.registration.CSRegistrations.registrations"]},{"name":"var isCanceled: Boolean = false","description":"renetik.android.event.registration.CSRegistrations.isCanceled","location":"renetik-android-event/renetik.android.event.registration/-c-s-registrations/is-canceled.html","searchKeys":["isCanceled","var isCanceled: Boolean = false","renetik.android.event.registration.CSRegistrations.isCanceled"]},{"name":"var isDestroyed: Boolean = false","description":"renetik.android.event.common.CSContext.isDestroyed","location":"renetik-android-event/renetik.android.event.common/-c-s-context/is-destroyed.html","searchKeys":["isDestroyed","var isDestroyed: Boolean = false","renetik.android.event.common.CSContext.isDestroyed"]}]
